Metadata-Version: 1.0
Name: error101
Version: 0.0.0
Summary: Python package for a cli tool for seamless debugging on the go.
Home-page: https://github.com/rohanbanerjee/solverror
Author: Rohan Banerjee
Author-email: banerjee.rohan98@gmail.com
License: MIT
Platform: UNKNOWN
